egit/__init__.py
egit/config/app_config.yml
egit/config/git_repos_config.json
egit/egit.py
egit/git_branch.py
egit/git_clone.py
egit/git_edit.py
egit/git_push.py
egit/logs/.logs
egit/target/.target
egit-2.0.0.dist-info/entry_points.txt
egit-2.0.0.dist-info/LICENSE
egit-2.0.0.dist-info/WHEEL
egit-2.0.0.dist-info/METADATA
egit-2.0.0.dist-info/RECORD
