Metadata-Version: 2.1
Name: egit
Version: 2.0.0
Summary: e(g)it is an app for replacing text in files across multiple GitHub repositories.
Home-page: https://github.com/datadlog/egit
License: MIT
Author: Naveen Thurimerla
Author-email: nawinto99@gmail.com
Maintainer: Naveen Thurimerla
Maintainer-email: nawinto99@gmail.com
Requires-Python: >=3.8,<4.0
Classifier: License :: OSI Approved :: MIT License
Classifier: Programming Language :: Python :: 3
Classifier: Programming Language :: Python :: 3.10
Classifier: Programming Language :: Python :: 3.8
Classifier: Programming Language :: Python :: 3.9
Provides-Extra: dev
Provides-Extra: doc
Provides-Extra: test
Requires-Dist: GitPython (>=3.1.18,<4.0.0)
Requires-Dist: PyYAML (>=5.4.1,<6.0.0)
Requires-Dist: black (>=21.6b0,<22.0); extra == "test"
Requires-Dist: flake8 (>=3.9.2,<4.0.0); extra == "test"
Requires-Dist: isort (>=5.9.1,<6.0.0); extra == "test"
Requires-Dist: mkdocs (>=1.2.1,<2.0.0); extra == "doc"
Requires-Dist: mkdocs-autorefs (>=0.2.1,<0.3.0); extra == "doc"
Requires-Dist: mkdocs-include-markdown-plugin (>=3.1.4,<4.0.0); extra == "doc"
Requires-Dist: mkdocs-material (>=7.1.9,<8.0.0); extra == "doc"
Requires-Dist: mkdocs-material-extensions (>=1.0.1,<2.0.0); extra == "doc"
Requires-Dist: mkdocstrings (>=0.15.2,<0.16.0); extra == "doc"
Requires-Dist: pip (>=21.1.3,<22.0.0); extra == "dev"
Requires-Dist: pytest (>=6.2.4,<7.0.0); extra == "test"
Requires-Dist: pytest-cov (>=2.12.1,<3.0.0); extra == "test"
Requires-Dist: toml (>=0.10.2,<0.11.0); extra == "dev"
Requires-Dist: tox (>=3.23.1,<4.0.0); extra == "dev"
Requires-Dist: twine (>=3.4.1,<4.0.0); extra == "dev"
Requires-Dist: virtualenv (>=20.4.7,<21.0.0); extra == "dev"
Project-URL: Bug Tracker, https://github.com/datadlog/egit/issues
Project-URL: Documentation, https://datadlog.github.io/egit/
Project-URL: Repository, https://github.com/datadlog/egit
